Workbook
Name Aporte: Simulacao_FIIs!$D$17
Name Patrimonio: Simulacao_FIIs!$D$20
Name Quantidade_anos: Simulacao_FIIs!$D$18
Name Rendimento_Carteira: Simulacao_FIIs!$D$13
Name Salario: Simulacao_FIIs!$D$12
Name Sugestao_investimento: Simulacao_FIIs!$D$14
Name Taxa_mensal: Simulacao_FIIs!$D$19

Sheet Simulacao_FIIs
B11: CONFIGURAÇÕES
B12: Salário | D12: 4200
B13: Rendimento Carteira | D13: 0.006
B14: Sugestão de Investimento | D14: =D12*30% -> 1260
B16: INVESTIMENTO MESAL
B17: Quanto investir por mês? | D17: 1260
B18: Por quantos anos? | D18: 10
B19: Taxa de rendimento mensal ? | D19: 0.01079
B20: Patrimonio Acumulado ? | D20: =FV(Taxa_mensal,Quantidade_anos*12,Aporte*-1) -> 306538.11
B21: Dividendos mensais? | D21: =D20*Rendimento_Carteira -> 1839.2286
B23: Cenários | D23: Dividendo
A24: 2 | B24: Quanto em 2 anos? | C24: =FV($D$19,A24*12,$D$17*-1) -> 34306.81 | D24: =C24*Rendimento_Carteira -> 205.84086
A25: 5 | B25: Quanto em 5 anos? | C25: =FV($D$19,A25*12,$D$17*-1) -> 105558.91 | D25: =C25*Rendimento_Carteira -> 633.35347
A26: 10 | B26: Quanto em 10 anos? | C26: =FV($D$19,A26*12,$D$17*-1) -> 306538.11 | D26: =C26*Rendimento_Carteira -> 1839.2286
A27: 20 | B27: Quanto em 20 anos? | C27: =FV($D$19,A27*12,$D$17*-1) -> 1417750 | D27: =C27*Rendimento_Carteira -> 8506.4999
A28: 30 | B28: Quanto em 30 anos? | C28: =FV($D$19,A28*12,$D$17*-1) -> 5445933.8 | D28: =C28*Rendimento_Carteira -> 32675.603
B32: PERFIL | C32: Moderado
B33: VALOR A SER INVESTIDO POR MÊS | C33: =Aporte -> 1260
B35: TIPO DE FII | C35: Percentual Sugerido | D35: Valores
B36: PAPEL | C36: =VLOOKUP($C$32&"-"&B36,Planilha2!$A$1:$D$20,4,FALSE) -> 0.32 | D36: =$C$33*C36 -> 403.2
B37: TIJOLO | C37: =VLOOKUP($C$32&"-"&B37,Planilha2!$A$1:$D$20,4,FALSE) -> 0.35 | D37: =$C$33*C37 -> 441
B38: HÍBRIDOS | C38: =VLOOKUP($C$32&"-"&B38,Planilha2!$A$1:$D$20,4,FALSE) -> 0.08 | D38: =$C$33*C38 -> 100.8
B39: FOFs | C39: =VLOOKUP($C$32&"-"&B39,Planilha2!$A$1:$D$20,4,FALSE) -> 0.05 | D39: =$C$33*C39 -> 63
B40: DESENVOLVIMENTO | C40: =VLOOKUP($C$32&"-"&B40,Planilha2!$A$1:$D$20,4,FALSE) -> 0.1 | D40: =$C$33*C40 -> 126
B41: HOTELARIAS | C41: =VLOOKUP($C$32&"-"&B41,Planilha2!$A$1:$D$20,4,FALSE) -> 0.1 | D41: =$C$33*C41 -> 126
D42: =SUM(D36:D41) -> 1260

Sheet Planilha3

Sheet Planilha2
A2: CHAVE | B2: perfil | C2: TIPO DE FII | D2: %
A3: =B3&"-"&C3 -> Conservador-PAPEL | B3: Conservador | C3: PAPEL | D3: 0.3
A4: =B4&"-"&C4 -> Conservador-TIJOLO | B4: Conservador | C4: TIJOLO | D4: 0.5
A5: =B5&"-"&C5 -> Conservador-HÍBRIDOS | B5: Conservador | C5: HÍBRIDOS | D5: 0.1
A6: =B6&"-"&C6 -> Conservador-FOFs | B6: Conservador | C6: FOFs | D6: 0.1
A7: =B7&"-"&C7 -> Conservador-DESENVOLVIMENTO | B7: Conservador | C7: DESENVOLVIMENTO | D7: 0
A8: =B8&"-"&C8 -> Conservador-HOTELARIAS | B8: Conservador | C8: HOTELARIAS | D8: 0
A9: =B9&"-"&C9 -> Moderado-PAPEL | B9: Moderado | C9: PAPEL | D9: 0.32
A10: =B10&"-"&C10 -> Moderado-TIJOLO | B10: Moderado | C10: TIJOLO | D10: 0.35
A11: =B11&"-"&C11 -> Moderado-HÍBRIDOS | B11: Moderado | C11: HÍBRIDOS | D11: 0.08
A12: =B12&"-"&C12 -> Moderado-FOFs | B12: Moderado | C12: FOFs | D12: 0.05
A13: =B13&"-"&C13 -> Moderado-DESENVOLVIMENTO | B13: Moderado | C13: DESENVOLVIMENTO | D13: 0.1
A14: =B14&"-"&C14 -> Moderado-HOTELARIAS | B14: Moderado | C14: HOTELARIAS | D14: 0.1
... A20: =B20&"-"&C20 -> Agressivo-HOTELARIAS | B20: Agressivo | C20: HOTELARIAS | D20: 0.1
